.bzrignore
.gitignore
CHANGES.txt
COPYRIGHT.txt
LICENSE.txt
README.txt
TODO.txt
setup.cfg
setup.py
tox.ini
compoze/__init__.py
compoze/_compat.py
compoze/compozer.py
compoze/fetcher.py
compoze/index.py
compoze/indexer.py
compoze/informer.py
compoze/pooler.py
compoze.egg-info/PKG-INFO
compoze.egg-info/SOURCES.txt
compoze.egg-info/dependency_links.txt
compoze.egg-info/entry_points.txt
compoze.egg-info/not-zip-safe
compoze.egg-info/requires.txt
compoze.egg-info/top_level.txt
compoze/tests/__init__.py
compoze/tests/test_compozer.py
compoze/tests/test_fetcher.py
compoze/tests/test_index.py
compoze/tests/test_indexer.py
compoze/tests/test_informer.py
compoze/tests/test_pooler.py
compoze/tests/fixtures/archive/1.txt
compoze/tests/fixtures/archive/folder.bz2
compoze/tests/fixtures/archive/folder.egg
compoze/tests/fixtures/archive/folder.tar.gz
compoze/tests/fixtures/archive/folder.tgz
compoze/tests/fixtures/archive/folder.zip
compoze/tests/fixtures/archive/folder/2.txt
docs/Makefile
docs/api.rst
docs/changes.rst
docs/commandline.rst
docs/conf.py
docs/configuration.rst
docs/glossary.rst
docs/index.rst
docs/install.rst
docs/narr.rst
docs/.static/logo_hi.gif
docs/.static/repoze.css